transport/__init__.py
transport/bus.py
transport/taxi.py
transport/train.py
transport/transport.py
lta_sg-0.0.1.dist-info/METADATA
lta_sg-0.0.1.dist-info/WHEEL
lta_sg-0.0.1.dist-info/licenses/LICENSE
lta_sg-0.0.1.dist-info/RECORD
